delceshi2/__init__.py
delceshi2/main.cpython-311-darwin.so
delceshi2/timer.cpython-311-darwin.so
delceshi2-0.1.0.dist-info/LICENCE.txt
delceshi2-0.1.0.dist-info/METADATA
delceshi2-0.1.0.dist-info/WHEEL
delceshi2-0.1.0.dist-info/entry_points.txt
delceshi2-0.1.0.dist-info/top_level.txt
delceshi2-0.1.0.dist-info/RECORD
