Metadata-Version: 2.1
Name: delceshi2
Version: 0.1.0
Summary: A package that returns 0.01 and uninstalls itself after 3 minutes.
Home-page: https://github.com/yourusername/self_deleting_package
Author: Your Name
Author-email: your.email@example.com
Classifier: Programming Language :: Python :: 3
Classifier: License :: OSI Approved :: MIT License
Classifier: Operating System :: OS Independent
Requires-Python: >=3.6
License-File: LICENCE.txt
